{"card_name": "Raiding Gnoll-Band", "color": "BR", "rarity": "rare", "type": "Creature \u2013 Hyena Rogue", "number": 221, "color_identity": "BR", "cost": "{2}{BR}{BR}", "rules_text": "Whenever an Aura you control becomes attached to a creature, choose one \u2013\n\u2022 Raiding Gnoll-Band deals 3 damage to that creature.\n\u2022 That creature gets +3/+0 until end of turn.", "flavor_text": "[i][/i]", "pt": "4/3", "special_text": "", "shape": "normal", "set": "KOD", "loyalty": "", "artist": "Geoff Glover", "notes": "", "image_type": "png"}