{"card_name": "Slimefoot Knight", "color": "G", "rarity": "common", "type": "Enchantment Creature \u2013 Frog Knight", "number": 192, "color_identity": "G", "cost": "{3}{G}", "rules_text": "Ward {2} [i](Whenever this creature becomes the target of a spell or ability an opponent controls, counter it unless that player pays {2}.)[/i]", "pt": "3/2", "special_text": "", "shape": "adventure", "set": "KND", "loyalty": "", "card_name2": "Hop-Along", "color2": "G", "type2": "Sorcery \u2013 Tale", "cost2": "{1}{G}", "rules_text2": "Create a 2/1 green and blue Frog creature token with ward {2}. [i](Cast a copy of this once while this is on the battlefield.)[/i]", "pt2": "", "special_text2": "", "loyalty2": "", "notes": ""}