{"card_name": "Blade of the Free", "color": "WR", "rarity": "rare", "type": "Artifact \u2013 Equipment", "number": 207, "color_identity": "WR", "cost": "{2}{R}{W}", "rules_text": "When Blade of the Free enters the battlefield, look at the top seven cards of your library. You may put creature card with mana value 3 or less from among them onto the battlefield and attach Blade of the Free to it. Put the rest on the bottom of your library in a random order.\nEquipped creature has double strike.\nEquip {2}", "pt": "", "special_text": "", "shape": "normal", "set": "KND", "loyalty": "", "notes": ""}