{"card_name": "Curse of Admonishment", "color": "B", "rarity": "common", "type": "Enchantment \u2013 Aura Curse", "number": 70, "color_identity": "B", "cost": "{2}{B}", "rules_text": "Enchant opponent\nAt the beginning of enchanted player's upkeep, they lose 1 life and you gain 1 life.", "flavor_text": "[i]\u201cAye, I see nothin' but black from that side, but I won't hide in shame behind a patch. The Admiral deserves to see his handiwork as I run my sword clean through his heart.\u201d[/i]", "pt": "", "special_text": "", "shape": "normal", "set": "GSS", "loyalty": "", "artist": "tinybutterfly", "notes": "UB:\n - even MV only\n - Zombies\nBR:\n - Five curses\n - Curses\nWB:\n - triggered abilities\n - flicker\nBG:\n - mana value 3 or greater\n - graveyard (lands)", "image_type": "png"}