{"card_name": "Noxious Smuggler", "color": "B", "rarity": "common", "type": "Creature \u2013 Goblin Rogue", "number": 111, "color_identity": "B", "cost": "{1}{B}", "rules_text": "When Noxious Smuggler dies, hoard. [i](Create a Treasure token. If you control at least two Treasures, you may draw a card instead.)[/i]", "flavor_text": "[i]His stench keeps others at a wide berth, perfect for his particular line of work.[/i]", "pt": "2/1", "special_text": "", "shape": "normal", "set": "FAU", "loyalty": "", "artist": "Alexander Kozachenko", "notes": "f!ub", "image_type": "png"}