{"card_name": "Wurtnook Firebrewer", "color": "R", "rarity": "uncommon", "type": "Creature \u2013 Goblin Shaman", "number": 166, "color_identity": "R", "cost": "{2}{R}", "rules_text": "When Wurtnook Firebrewer enters the battlefield, you may put a basic land card from your hand onto the battlefield with two +1/+1 counters on it. If you do, it becomes a 0/0 red Elemental creature with haste and \u201cWhen this creature dies, return it to its owner's hand.\u201d", "flavor_text": "[i][/i]", "pt": "2/2", "special_text": "", "shape": "normal", "set": "FAU", "loyalty": "", "artist": "Bruno Jacob", "notes": "f!rg", "image_type": "png"}