{"card_name": "Skitter of Spiders", "color": "B", "rarity": "uncommon", "type": "Sorcery", "number": 98, "color_identity": "BG", "cost": "{2}{B}", "rules_text": "Create two 1/2 green Spider creature tokens with reach.\nPromote {6}{G} [i](You may cast this card from your graveyard for its promote cost. If you do, double all numbers and number words on it. Then exile it.)[/i]", "flavor_text": "[i][/i]", "pt": "", "special_text": "", "shape": "normal", "set": "MVA", "loyalty": "", "artist": "J Wardle-Parker", "notes": "", "image_type": "png"}