{"card_name": "Bloodboil Harlequin", "color": "R", "rarity": "uncommon", "type": "Creature \u2013 Mutant Shaman", "number": 115, "color_identity": "R", "cost": "{2}{R}{R}", "rules_text": "Haste\nDesecrate [i](When this creature enters, you may sacrifice an artifact or land.)[/i]\nWhen Bloodboil Harlequin desecrates a permanent, up to two target creatures can't block this turn.", "flavor_text": "[i][/i]", "pt": "4/2", "special_text": "", "shape": "normal", "set": "ATB", "loyalty": "", "artist": "Michele Giorgi", "notes": "", "image_type": "png"}