{"card_name": "Sahalia Dragoons", "color": "G", "rarity": "uncommon", "type": "Creature \u2013 Mutant Warrior", "number": 176, "color_identity": "G", "cost": "{3}{G}{G}", "rules_text": "Vigilance\n{1}{G}{G}: Sahalia Dragoons gets +4/+4 until end of turn. Activate only once each turn.", "flavor_text": "[i]Suraj outriders know a befriended beast is far more useful than a pet.[/i]", "pt": "4/4", "special_text": "", "shape": "normal", "set": "ATB", "loyalty": "", "artist": "Alejandro Arevalo", "notes": "", "image_type": "png"}