{"card_name": "Shawlbinder", "color": "W", "rarity": "uncommon", "type": "Creature \u2013 Human", "number": 32, "color_identity": "W", "cost": "{1}{W}", "rules_text": "When Shawlbinder enters, if you control a Desert, exile another target permanent. Return that card to the battlefield under its owner's control at the beginning of the next end step.", "flavor_text": "[i][/i]", "pt": "3/1", "special_text": "", "shape": "normal", "set": "ATB", "loyalty": "", "artist": "Aaron Miller", "notes": "", "image_type": "png"}