{"card_name": "Acrobatic Maneuver", "color": "W", "rarity": "common", "type": "Instant", "number": 3, "color_identity": "W", "cost": "{2}{W}", "rules_text": "Exile target creature you control, then return that card to the battlefield under its owner's control.\nDraw a card.", "flavor_text": "[i]For the vampires of the Consortium, nothing elicits joy like a dance on a fresh grave.[/i]", "pt": "", "special_text": "", "shape": "normal", "set": "TWB", "loyalty": "", "artist": "Irina Kuzmina", "notes": "reprint", "image_type": "png"}