{"card_name": "Frozen Skies", "color": "G", "rarity": "common", "type": "Sorcery", "number": 172, "color_identity": "G", "cost": "{2}{G}", "rules_text": "Destroy target creature with flying. Other creatures with flying can't block this turn.", "flavor_text": "[i]The ice freezes up the wings of dragons, and they crack and shatter in the wind.[/i]", "pt": "", "special_text": "", "shape": "normal", "set": "GLC", "loyalty": "", "artist": "Lulztroll87 on DeviantART", "notes": "", "image_type": "jpg"}