{"card_name": "Glacial Demon", "color": "B", "rarity": "uncommon", "type": "Snow Creature \u2013 Demon", "number": 96, "color_identity": "B", "cost": "{2}{B}{B}", "rules_text": "Intimidate [i](This creature can't be blocked except by artifact creatures and/or creatures that share a color with it.)[/i]\nWhen Glacial Demon enters the battlefield, sacrifice all other creatures you control.", "flavor_text": "[i]\u201cBow to me, then die!\u201d[/i]", "pt": "5/5", "special_text": "", "shape": "normal", "set": "GLC", "loyalty": "", "artist": "Jonathan Gragg", "notes": "", "image_type": "jpg"}