{"card_name": "Inspirited Duelist", "color": "W", "rarity": "uncommon", "type": "Creature \u2013 Human Warrior", "number": 16, "color_identity": "W", "cost": "{1}{W}", "rules_text": "Inspirited Duelist has double strike as long as it has a +1/+1 counter on it.", "flavor_text": "[i]\u201cI do not fight for pride, nor pleasure, nor honor. I fight to defend my brothers and sisters who cannot defend themselves.\u201d[/i]", "pt": "1/2", "special_text": "", "shape": "normal", "set": "SUR", "loyalty": "", "artist": "Wang Lei", "notes": "", "image_type": "jpg"}