{"card_name": "Overflowing Vitae", "color": "R", "rarity": "common", "type": "Sorcery", "number": 127, "color_identity": "R", "cost": "{1}{R}", "rules_text": "Choose one \u2013\n\u2022 Overflowing Vitae deals 3 damage to target player or planeswalker.\n\u2022 Exile target artifact.", "flavor_text": "[i]\u201cI still don't know why this dial goes to 11, but I now see that it is, in fact, too much juice.\u201d\n\u2014Vernus Prioleau, Master Tinker[/i]", "pt": "", "special_text": "", "shape": "normal", "set": "WAS", "loyalty": "", "artist": "Elder Scrolls: Legends", "notes": "!quote", "image_type": "png"}