{"card_name": "Mohr, the Twisted Wind", "color": "UG", "rarity": "rare", "type": "Legendary Creature \u2013 Mutant Shaman", "number": 200, "color_identity": "UG", "cost": "{G}{U}", "rules_text": "Flash\nYou may have Mohr enter the battlefield as a copy of any permanent with mana value 3 or less on the battlefield, except it has \u201c{4}: Return this to its owner's hand.\u201d\n{4}: Return Mohr to their owner's hand.", "flavor_text": "[i][/i]", "pt": "2/2", "special_text": "", "shape": "normal", "set": "WAS", "loyalty": "", "artist": "Karl Simon", "notes": "", "image_type": "png"}