{"card_name": "Tin Woodsman", "color": "W", "rarity": "common", "type": "Artifact Creature \u2013 Construct", "number": 33, "color_identity": "W", "cost": "{2}{W}", "rules_text": "When Tin Woodsman dies, proliferate. [i](Choose any number of permanents and/or players, then give each another counter of each kind already there.)[/i]", "flavor_text": "[i]\u201cIn each Transplant, I see perfection\u2014what once labored under its own complexity now simplified to a single directive and a quiet whirr.\u201d\n\u2014Vernus Prioleau, Master Tinker[/i]", "pt": "3/2", "special_text": "", "shape": "normal", "set": "WAS", "loyalty": "", "artist": "Josh Guglielmo", "notes": "!quote", "image_type": "png"}