{"card_name": "Soul Threader", "color": "W", "rarity": "common", "type": "Creature \u2013 Human Cleric", "number": 23, "color_identity": "W", "cost": "{3}{W}", "rules_text": "Lifelink\n[i]Penance[/i] \u2013 {2}{W}, Sacrifice Soul Threader: You gain 6 life.", "flavor_text": "[i]\u201cRestoration efforts have, to this point, been unsuccessful. By the New Gods' mercy, may we continue trying.\u201d[/i]", "pt": "3/2", "special_text": "", "shape": "normal", "set": "AOD", "loyalty": "", "artist": "Heroes of Might and Magic", "notes": "", "image_type": "jpg"}