{"card_name": "Ceremonial Jian", "color": "R", "rarity": "common", "type": "Artifact \u2013 Equipment", "number": 128, "color_identity": "R", "cost": "{R}", "rules_text": "Golden age [i](If you cast an instant or sorcery spell, activated a nonmana ability, and attacked this turn, enter a renaissance for this game.)[/i]\nEquipped creature gets +2/+0.\nAs long as you\u2019re in a renaissance, equipped creature has first strike.\nEquip {3}", "pt": "", "special_text": "", "shape": "normal", "set": "NJB", "loyalty": "", "notes": ""}