{"card_name": "For the Court of the Queen", "color": "R", "rarity": "uncommon", "type": "Enchantment", "number": 139, "color_identity": "R", "cost": "{2}{R}", "rules_text": "Whenever you cast an instant or sorcery spell, if you cast it for its showcase cost, exile the top two cards of your library. Otherwise, look at the top two cards of your library, then put one on the bottom of your library and exile the other. You may play cards exiled this way until you exile one or more other cards with For the Court of the Queen.", "pt": "", "special_text": "", "shape": "normal", "set": "NJB", "loyalty": "", "notes": ""}