{"card_name": "Verdant Druid", "color": "G", "rarity": "uncommon", "type": "Creature \u2013 Human Druid", "number": 201, "color_identity": "G", "cost": "{2}{G}", "rules_text": "Golden age [i](If you cast an instant or sorcery spell, activated a nonmana ability, and attacked this turn, enter a renaissance for this game.)[/i]\n{2}{G}: Reveal the top three cards of your library. You may put a creature card from among them on top. If you\u2019re in a renaissance, put it into your hand instead. Put the rest on the bottom of in any order.", "pt": "3/2", "special_text": "", "shape": "normal", "set": "NJB", "loyalty": "", "notes": ""}