{"card_name": "Apostle of the Elders", "color": "W", "rarity": "common", "type": "Creature \u2013 Human Warrior", "number": 4, "color_identity": "W", "cost": "{3}{W}", "rules_text": "Apostle of the Elders has lifelink as long as it has a +1/+1 counter on it.", "flavor_text": "[i]\u201cI will join you at the festival, and I will celebrate, but not before I honor those who fought so that I could.\u201d[/i]", "pt": "3/3", "special_text": "", "shape": "normal", "set": "NJB", "loyalty": "", "artist": "Hou China", "notes": "", "image_type": "png"}