{"card_name": "Ehnit's Slave Chains", "color": "", "rarity": "rare", "type": "Legendary Artifact", "number": 226, "color_identity": "C", "cost": "{5}", "rules_text": "You may choose not to untap Ehnit's Slave Chains during your untap step.\n{X}, {T}: Gain control of target creature with power X or less for as long as Ehnit's Slave Chains remains tapped. Untap that creature. It gains haste until end of turn.", "flavor_text": "[i][/i]", "pt": "", "special_text": "", "shape": "normal", "set": "ICH", "loyalty": "", "artist": "Abigail Aidelbaum", "notes": "", "image_type": "jpg"}