{"card_name": "Oppressive Rays", "color": "W", "rarity": "common", "type": "Enchantment \u2013 Aura", "number": 28, "color_identity": "W", "cost": "{W}", "rules_text": "Enchant creature\nEnchanted creature can't attack or block unless its controller pays {3}.\nActivated abilities of enchanted creature cost {3} more to activate.", "flavor_text": "[i][/i]", "pt": "", "special_text": "", "shape": "normal", "set": "ICH", "loyalty": "", "artist": "Facundo Diaz", "notes": "**REPRINT**", "image_type": "jpg"}