{"card_name": "Fervid Desecration", "color": "R", "rarity": "common", "type": "Sorcery", "number": 109, "color_identity": "R", "cost": "{2}{R}", "rules_text": "As an additional cost to cast this spell, discard a card.\nExile the top three cards of your library. You may play those cards until the end of your next turn.", "flavor_text": "[i]\u201cReborn? No. Repurposed.\u201d[/i]", "pt": "", "special_text": "", "shape": "normal", "set": "SGB", "loyalty": "", "artist": "Igor Burlakov", "notes": "", "image_type": "png"}