{"card_name": "Avrithe, Wayward Empress", "color": "B", "rarity": "uncommon", "type": "Legendary Creature \u2013 Vampire Noble", "number": 71, "color_identity": "B", "cost": "{4}{B}{B}", "rules_text": "Flying\n[i]Menagerie[/i] \u2013 When Avrithe enters the battlefield, if there are five or more creature types among creatures you control, search your library for a card, put it into your hand, then shuffle.", "flavor_text": "[i]\u201cThe townsfolk cackled and booed as I was cast into exile. Well, who's laughing now?\u201d[/i]", "pt": "4/4", "special_text": "", "shape": "normal", "set": "SGB", "loyalty": "", "artist": "Antonio Manzanedo", "notes": "", "image_type": "png"}