{"card_name": "Wailing Stalker", "color": "", "rarity": "uncommon", "type": "Creature \u2013 Eldrazi", "number": 12, "color_identity": "C", "cost": "{7}", "rules_text": "Menace\nWhenever Wailing Stalker becomes blocked, defending player sacrifices a creature blocking it.", "flavor_text": "[i]The Eldrazi sing a chilling song of cold, concise finality.[/i]", "pt": "7/5", "special_text": "", "shape": "normal", "set": "GQC", "loyalty": "", "artist": "Daniel Aviles", "notes": "", "image_type": "png"}