{"card_name": "Bearer of Last Wishes", "color": "B", "rarity": "rare", "type": "Creature \u2013 Demon", "number": 97, "color_identity": "B", "cost": "{5}{B}{B}", "rules_text": "Flying\nWhen Bearer of Last Wishes enters the battlefield, you may discard your hand. If you do, search your library for two cards and put those cards into your hand, then shuffle your library.", "flavor_text": "[i][/i]", "pt": "7/7", "special_text": "", "shape": "normal", "set": "GQC", "loyalty": "", "artist": "Anton Grechko", "notes": "", "image_type": "png"}