{"card_name": "Equanimity", "color": "W", "rarity": "rare", "type": "Enchantment \u2013 Aura", "number": 15, "color_identity": "W", "cost": "{1}{W}", "rules_text": "Enchant creature\nAs Equanimity enters, choose a card type.\nWhen Equanimity enters, draw a card.\nEnchanted creature has protection from the chosen card type. This effect doesn't remove Equanimity. [i](This permanent can't be targeted, dealt damage, enchanted, or equipped by anything with that card type.)[/i]", "flavor_text": "[i][/i]", "pt": "", "special_text": "", "shape": "normal", "set": "GHQ", "loyalty": "", "artist": "Lucas Parolin", "notes": "", "image_type": "png"}