{"card_name": "Battle Roarer", "color": "G", "rarity": "uncommon", "type": "Creature \u2013 Bear Warrior", "number": 171, "color_identity": "G", "cost": "{1}{G}", "rules_text": "Vigilance\n{4}{G}{G}, {T}: Other creatures you control get +2/+2 until end of turn.", "flavor_text": "[i]Know how to fight, and you're useful. Know how to spur others to fight, and you're important. Know how to do both at the same time, and you're irreplaceable.[/i]", "pt": "2/2", "special_text": "", "shape": "normal", "set": "GHQ", "loyalty": "", "artist": "Rui Jin", "notes": "", "image_type": "png"}