{"card_name": "Rakkiri Piker", "color": "WR", "rarity": "uncommon", "type": "Creature \u2013 Fox Soldier", "number": 222, "color_identity": "WR", "cost": "{1}{R}{W}", "rules_text": "Rakkiri Piker has double strike as long as it's embattled. [i](A creature is embattled if it has a counter on it or has a permanent you control attached to it.)[/i]", "flavor_text": "[i]\u201cDouble the weapons, double the pain, and double the deterrent.\u201d[/i]", "pt": "2/3", "special_text": "", "shape": "normal", "set": "GHQ", "loyalty": "", "artist": "Jerome Jacinto", "notes": "", "image_type": "png"}