{"card_name": "Xiong Mao, the Intrepid", "color": "BRG", "rarity": "mythic", "type": "Legendary Planeswalker \u2013 Xiong Mao", "number": 225, "color_identity": "BRG", "cost": "{2}{B}{R}{G}", "rules_text": "", "flavor_text": "[i][/i]", "pt": "", "special_text": "[+2]: Create a 3/3 red Panda creature token.\n[-X]: Sacrifice a creature. If you do, search your library for a creature card with mana value less than or equal to X plus the sacrificed creature's mana value. Put that card onto the battlefield, then shuffle.\n[-6]: You get an emblem with \u201cWhenever a creature dies, this emblem deals damage equal to that creature's power to any target and you draw that many cards.\u201d", "shape": "planeswalker", "set": "GHQ", "loyalty": "3", "artist": "Alexander Zorin", "notes": "", "image_type": "png"}