{"card_name": "Holcomb of the Peregrine", "color": "UG", "rarity": "rare", "type": "Legendary Creature \u2013 Human Pirate", "number": 215, "color_identity": "UG", "cost": "{1}{G}{U}", "rules_text": "Vigilance\nWhenever you cast a spell with the same name as a card in your graveyard, draw a card.", "flavor_text": "[i][/i]", "pt": "3/3", "special_text": "First mate\u2013Each nonland card in your starting deck has the same name as exactly one other card in your starting deck. [i](If this card outside the game is your chosen first mate, you may swap it with a card in your opening hand.)[/i]\nVigilance\nWhenever you cast a spell with the same name as a card in your graveyard, draw a card.", "shape": "normal", "set": "DSS", "loyalty": "", "artist": "Bob Kehl", "notes": "", "image_type": "png"}