{"card_name": "Hugo of the Shadowstaff", "color": "BR", "rarity": "rare", "type": "Legendary Creature \u2013 Human Pirate", "number": 216, "color_identity": "BR", "cost": "{B}{R}", "rules_text": "Menace\nOnce each turn, when one or more sources you control deal damage, you may put a +1/+1 counter on Hugo.", "flavor_text": "[i][/i]", "pt": "1/1", "special_text": "First mate\u2013Your starting deck contains only cards with mana value 0, 1, or 3. [i](If this card outside the game is your chosen first mate, you may swap it with a card in your opening hand.)[/i]\nMenace\nOnce each turn, when one or more sources you control deal damage, you may put a +1/+1 counter on Hugo.", "shape": "normal", "set": "DSS", "loyalty": "", "artist": "Anry Nemo", "notes": "", "image_type": "png"}