{"card_name": "Sink", "color": "U", "rarity": "common", "type": "Instant", "number": 73, "color_identity": "U", "cost": "{2}{U}{U}", "rules_text": "Counter target spell.\nForebode. [i](Create a tapped colorless Omen artifact token with \u201c{T}, Discard a card, Sacrifice this artifact: Draw a card.\u201d)[/i]", "flavor_text": "[i]\u201cAny news on the [/i]Dauntless, [i]Ashcroft?\u201d\n\u201cI'm sorry, sir. Lost at sea.\u201d[/i]", "pt": "", "special_text": "", "shape": "normal", "set": "DSS", "loyalty": "", "artist": "Dimitrije Miljus", "notes": "", "image_type": "png"}