{"card_name": "Dusk Lieutenant", "color": "B", "rarity": "rare", "type": "Creature \u2013 Skeleton Pirate", "number": 93, "color_identity": "B", "cost": "{1}{B}{B}", "rules_text": "When Dusk Lieutenant enters, forebode. [i](Create a tapped colorless Omen artifact token with \u201c{T}, Discard a card, Sacrifice this artifact: Draw a card.\u201d)[/i]\nOnce each turn, when you discard a card during your turn, each opponent discards a card.", "flavor_text": "[i][/i]", "pt": "4/2", "special_text": "", "shape": "normal", "set": "DSS", "loyalty": "", "artist": "Ryan Yen", "notes": "", "image_type": "png"}