{"card_name": "Disrupt the Masses", "color": "R", "rarity": "common", "type": "Sorcery", "number": 101, "color_identity": "R", "cost": "{5}{R}{R}", "rules_text": "Creatures you control get +2/+0 until end of turn.\nCreatures with power 2 or less can't block this turn.", "flavor_text": "[i]\u201cLet the golems charge in first. We can move in after and clean up what's left.\u201d[/i]", "pt": "", "special_text": "", "shape": "normal", "set": "MSR", "loyalty": "", "artist": "Elena Dudina", "notes": "U/R card", "image_type": "jpg"}