{"card_name": "Maniacal Scourge", "color": "R", "rarity": "rare", "type": "Creature \u2013 Devil", "number": 112, "color_identity": "R", "cost": "{R}", "rules_text": "Whenever a red instant or sorcery spell you control deals damage to a creature or player, Maniacal Scourge gets +X/+0 until end of turn, where X is equal to the damage dealt.", "flavor_text": "[i][/i]", "pt": "1/1", "special_text": "", "shape": "normal", "set": "MSR", "loyalty": "", "artist": "Mikey Petrov", "notes": "", "image_type": "jpg"}