{"card_name": "Mimic of the Coyote", "color": "G", "rarity": "common", "type": "Creature \u2013 Human Shaman", "number": 137, "color_identity": "G", "cost": "{3}{G}", "rules_text": "When Mimic of the Coyote enters the battlefield, put a +1/+1 counter on target creature you control, then proliferate.", "flavor_text": "[i]Always searching for answers, the shamans have delved into the minds of animals. One has chosen the coyote, attempting to understand the thrill of the hunt.[/i]", "pt": "2/1", "special_text": "", "shape": "normal", "set": "MSR", "loyalty": "", "artist": "bloodrizer (DA)", "notes": "U/G card", "image_type": "jpg"}