{"card_name": "Woolly Tarantula", "color": "G", "rarity": "common", "type": "Creature \u2013 Spider", "number": 157, "color_identity": "G", "cost": "{1}{G}", "rules_text": "Reach\nPrevent all damage that would be dealt to Woolly Tarantula by creatures with flying.", "flavor_text": "[i]\u201cThe point at which I saw spider webs, strung 50 feet in the air, was the point at which I realized I should leave the Aghesh jungle and never return.\u201d[/i]", "pt": "3/1", "special_text": "", "shape": "normal", "set": "MSR", "loyalty": "", "artist": "Robert Berrier", "notes": "B/G card", "image_type": "jpg"}