{"card_name": "Study the Tradewinds", "color": "U", "rarity": "rare", "type": "Instant", "number": 61, "color_identity": "U", "cost": "{U}", "rules_text": "Kicker {1}{U} [i](You may pay an additional {1}{U} as you cast this spell.)[/i]\nDraw a card.\nIf Study the Tradewinds was kicked, whenever you cast another instant or sorcery spell this turn, draw a card.", "flavor_text": "[i][/i]", "pt": "", "special_text": "", "shape": "normal", "set": "MSR", "loyalty": "", "artist": "Smolin (DA)", "notes": "", "image_type": "jpg"}