{"card_name": "Riddle of the Crypt", "color": "B", "rarity": "rare", "type": "Sorcery", "number": 84, "color_identity": "B", "cost": "{B}", "rules_text": "Kicker {2}{B} [i](You may pay an additional {2}{B} as you cast this spell.)[/i]\nSearch your library for a card and put that card into your graveyard, then shuffle your library. If Riddle of the Crypt was kicked, instead search your library for a card and put that card into your hand, then shuffle your library.", "flavor_text": "[i][/i]", "pt": "", "special_text": "", "shape": "normal", "set": "MSR", "loyalty": "", "artist": "Ishutani (DA)", "notes": "", "image_type": "jpg"}