{"card_name": "Hatsuo, Honored General", "color": "R", "rarity": "rare", "type": "Legendary Creature \u2013 Human Warrior", "number": 153, "color_identity": "R", "cost": "{2}{R}{R}", "rules_text": "First strike\n{1}{R}: Hatsuo, Honored General and other Warrior creatures you control get +1/+0 until end of turn.", "flavor_text": "[i]\u201cBravery is simply well-managed fear.\u201d[/i]", "pt": "3/2", "special_text": "", "shape": "normal", "set": "GNJ", "loyalty": "", "artist": "Phoenix Lu", "notes": "", "image_type": "jpg"}