{"card_name": "Pious Flutist", "color": "W", "rarity": "common", "type": "Creature \u2013 Human Bard", "number": 31, "color_identity": "W", "cost": "{W}", "rules_text": "When Pious Flutist enters, create an Idol token. [i](It's an artifact with \u201c{1}, Sacrifice this artifact: Put a +1/+1 counter on target creature. Activate only as a sorcery.\u201d)[/i]", "flavor_text": "[i]Each night she plays a melody to Lijing, and each morning she awakens safely\u2014a cycle she dares not disturb.[/i]", "pt": "1/2", "special_text": "", "shape": "normal", "set": "GNJ", "loyalty": "", "artist": "Jandice Barov", "notes": "!update", "image_type": "jpg"}