{"card_name": "Unshaken Oak", "color": "", "rarity": "rare", "type": "Snow Land", "number": 274, "color_identity": "RG", "cost": "", "rules_text": "Unshaken Oak enters the battlefield tapped.\n{T}: Add {R} or {G}.\n{2}{S}{S}: Until end of turn, Unshaken Oak becomes a 5/4 red and green Elemental creature with \u201cWhenever this creature deals combat damage to an opponent, it deals damage equal to its power to target planeswalker that player controls.\u201d It's still a land.", "flavor_text": "[i][/i]", "pt": "", "special_text": "", "shape": "normal", "set": "AEX", "loyalty": "", "artist": "Maciej Janaszek", "notes": "", "image_type": "png"}