{"card_name": "Drink the Dark Blood", "color": "B", "rarity": "uncommon", "type": "Instant", "number": 85, "color_identity": "B", "cost": "{B}", "rules_text": "Traverse Ghariv. [i](Planeswalk to Ghariv. If you're already there, cause {A}.)[/i]", "flavor_text": "[i]\u201cYou have a choice to make. Walk away into a life of mediocrity, or drink from the goblet and realize His destiny.\u201d[/i]", "pt": "", "special_text": "", "shape": "normal", "set": "AEX", "loyalty": "", "artist": "Michael Komarck", "notes": "", "image_type": "png"}